Techv_ai/__init__.py
Techv_ai/chat.py
Techv_ai/client.py
Techv_ai/models.json
Techv_ai/routeing.py
techv_ai-3.2.1.dist-info/licenses/LICENCE
techv_ai-3.2.1.dist-info/METADATA
techv_ai-3.2.1.dist-info/WHEEL
techv_ai-3.2.1.dist-info/entry_points.txt
techv_ai-3.2.1.dist-info/top_level.txt
techv_ai-3.2.1.dist-info/RECORD
