Metadata-Version: 2.4
Name: techv_ai
Version: 3.2.1
Summary: Techvantage AI Developer Toolkit
Author: Techvantage
Classifier: Programming Language :: Python :: 3
Classifier: License :: OSI Approved :: MIT License
Classifier: Operating System :: OS Independent
Requires-Python: >=3.8
License-File: LICENCE
Requires-Dist: msal>=1.24.0
Requires-Dist: requests>=2.28.0
Requires-Dist: openai
Requires-Dist: groq
Dynamic: author
Dynamic: classifier
Dynamic: description
Dynamic: description-content-type
Dynamic: license-file
Dynamic: requires-dist
Dynamic: requires-python
Dynamic: summary
